odoo/addons/fieldservice_sale_recurring_agreement/README.rst
odoo/addons/fieldservice_sale_recurring_agreement/__init__.py
odoo/addons/fieldservice_sale_recurring_agreement/__manifest__.py
odoo/addons/fieldservice_sale_recurring_agreement/i18n/fieldservice_sale_recurring_agreement.pot
odoo/addons/fieldservice_sale_recurring_agreement/i18n/it.po
odoo/addons/fieldservice_sale_recurring_agreement/models/__init__.py
odoo/addons/fieldservice_sale_recurring_agreement/models/fsm_recurring.py
odoo/addons/fieldservice_sale_recurring_agreement/models/sale_order_line.py
odoo/addons/fieldservice_sale_recurring_agreement/readme/CONTRIBUTORS.md
odoo/addons/fieldservice_sale_recurring_agreement/readme/DESCRIPTION.md
odoo/addons/fieldservice_sale_recurring_agreement/static/description/icon.png
odoo/addons/fieldservice_sale_recurring_agreement/static/description/index.html
odoo/addons/fieldservice_sale_recurring_agreement/views/fsm_recurring.xml
odoo_addon_fieldservice_sale_recurring_agreement-18.0.1.0.0.4.dist-info/METADATA
odoo_addon_fieldservice_sale_recurring_agreement-18.0.1.0.0.4.dist-info/WHEEL
odoo_addon_fieldservice_sale_recurring_agreement-18.0.1.0.0.4.dist-info/top_level.txt
odoo_addon_fieldservice_sale_recurring_agreement-18.0.1.0.0.4.dist-info/RECORD
